par_ocr/__init__.py
par_ocr/__main__.py
par_ocr/py.typed
par_ocr/system_prompt.md
par_ocr-0.2.0.dist-info/METADATA
par_ocr-0.2.0.dist-info/WHEEL
par_ocr-0.2.0.dist-info/entry_points.txt
par_ocr-0.2.0.dist-info/licenses/LICENSE
par_ocr-0.2.0.dist-info/RECORD
