Metadata-Version: 2.4
Name: par_ocr
Version: 0.2.0
Summary: Use AI vision to OCR PDF and image files to markdown.
Project-URL: Homepage, https://github.com/paulrobello/par_ocr
Project-URL: Documentation, https://github.com/paulrobello/par_ocr/blob/main/README.md
Project-URL: Repository, https://github.com/paulrobello/par_ocr
Project-URL: Issues, https://github.com/paulrobello/par_ocr/issues
Project-URL: Discussions, https://github.com/paulrobello/par_ocr/discussions
Project-URL: Wiki, https://github.com/paulrobello/par_ocr/wiki
Author-email: Paul Robello <probello@gmail.com>
Maintainer-email: Paul Robello <probello@gmail.com>
License: MIT License
License-File: LICENSE
Keywords: ai,markdown,ocr,pdf
Classifier: Development Status :: 4 - Beta
Classifier: Environment :: Console
Classifier: Intended Audience :: Developers
Classifier: License :: OSI Approved :: MIT License
Classifier: Programming Language :: Python :: 3
Classifier: Programming Language :: Python :: 3.11
Classifier: Programming Language :: Python :: 3.12
Classifier: Programming Language :: Python :: 3.13
Classifier: Topic :: Software Development :: Libraries :: Python Modules
Classifier: Topic :: Text Processing :: Markup :: Markdown
Classifier: Typing :: Typed
Requires-Python: >=3.11
Requires-Dist: asyncio>=3.4.3
Requires-Dist: par-ai-core>=0.1.11
Requires-Dist: pdf2image>=1.17.0
Requires-Dist: psycopg[binary]>=3.2.4
Requires-Dist: pydantic-core>=2.27.2
Requires-Dist: pydantic>=2.10.6
Requires-Dist: python-dotenv>=1.0.1
Requires-Dist: rich>=13.9.4
Requires-Dist: typer>=0.15.1
